abir_roy_package/__init__.py
abir_roy_package/model.py
abir_roy_package/data/__init__.py
abir_roy_package/data/dataset.py
abir_roy_package/data/download.py
abir_roy_package/data/transforms/__init__.py
abir_roy_package/data/transforms/blur.py
abir_roy_package/data/transforms/crop.py
abir_roy_package/data/transforms/flip.py
abir_roy_package/data/transforms/rescale.py
abir_roy_package/data/transforms/rotate.py
abir_roy_package-0.0.1.dist-info/METADATA
abir_roy_package-0.0.1.dist-info/WHEEL
abir_roy_package-0.0.1.dist-info/RECORD
